setup.py
jf_tokenize_package/tokenize.py
jf_tokenize_package.egg-info/PKG-INFO
jf_tokenize_package.egg-info/SOURCES.txt
jf_tokenize_package.egg-info/dependency_links.txt
jf_tokenize_package.egg-info/top_level.txt