Metadata-Version: 2.1
Name: jf-tokenize-package
Version: 1.0.3
Summary: A simple tokenizer function for NLP
Home-page: https://github.com/Granju/tokenize-package
Author: Julien Flandre
Author-email: julien.flandre@gmail.com
License: MIT
Keywords: tokenizer function
Platform: UNKNOWN
